esbmtk/Hypsometric_Curve_05m_100.csv
esbmtk/__init__.py
esbmtk/base_classes.py
esbmtk/carbonate_chemistry.py
esbmtk/connections.py
esbmtk/esbmtk_base.py
esbmtk/extended_classes.py
esbmtk/initialize_unit_registry.py
esbmtk/model.py
esbmtk/ode_backend_2.py
esbmtk/post_processing.py
esbmtk/processes.py
esbmtk/sealevel.py
esbmtk/seawater.py
esbmtk/species_definitions.py
esbmtk/utility_functions.py
esbmtk/version.py
esbmtk-0.14.2.12.dist-info/licenses/LICENSE.txt
esbmtk-0.14.2.12.dist-info/METADATA
esbmtk-0.14.2.12.dist-info/WHEEL
esbmtk-0.14.2.12.dist-info/top_level.txt
esbmtk-0.14.2.12.dist-info/RECORD
