Metadata-Version: 2.4
Name: esbmtk
Version: 0.14.2.12
Summary: The Earth Science Box Modeling Toolkit
Home-page: https://github.com/uliw/esbmtk
Author: Ulrich G. Wortmann
Author-email: uli.wortmann@utoronto.ca
License: GPL-3.0-or-later
Project-URL: Documentation, https://esbmtk.readthedocs.io/en/latest/
Project-URL: Source, https://github.com/uliw/esbmtk
Project-URL: Changelog, https://github.com/uliw/esbmtk/blob/master/CHANGELOG.rst
Platform: any
Classifier: Programming Language :: Python :: 3
Classifier: Operating System :: OS Independent
Classifier: Intended Audience :: Education
Classifier: Intended Audience :: Science/Research
Classifier: Topic :: Scientific/Engineering :: Chemistry
Requires-Python: >=3.12
License-File: LICENSE.txt
Requires-Dist: PyCO2SYS>=1.8.3.3
Requires-Dist: numpy
Requires-Dist: pandas
Requires-Dist: matplotlib
Requires-Dist: numba
Requires-Dist: pint
Requires-Dist: psutil
Requires-Dist: scipy
Requires-Dist: cachetools
Requires-Dist: setuptools
Requires-Dist: importlib-metadata
Provides-Extra: testing
Requires-Dist: setuptools; extra == "testing"
Requires-Dist: pytest; extra == "testing"
Dynamic: license-file
